{"tokens":[{"name":"LP-SETH-SWBTC","address":"secret1nvqrwwr9942gn89nk44nf2nku6gr7u8tsg6z45","decimals":6,"hidden":true,"usage":["LPSTAKING"],"price":"0","id":"lp-seth-swbtc","display_props":{"image":"/static/scrt.svg","symbol":"lp-seth-swbtc","label":"LP-SETH-SWBTC"},"_id":"662b76941fcacc2335cbe8e4"},{"name":"LP-SSCRT-SEFI","address":"secret1709qy2smh0r7jjac0qxfgjsqn7zpvgthsdz025","decimals":6,"hidden":true,"usage":["LPSTAKING"],"price":"0","id":"lp-sscrt-sefi","display_props":{"image":"/static/scrt.svg","symbol":"lp-sscrt-sefi","label":"LP-SSCRT-SEFI"},"_id":"662b76941fcacc520fcbe8e5"},{"name":"LP-SSCRT-SRSR","address":"secret102gfpp4hgvytxlxsz8hnjy7uqndmhau3jkzps8","decimals":6,"hidden":true,"usage":["LPSTAKING"],"price":"0","id":"lp-sscrt-srsr","display_props":{"image":"/static/scrt.svg","symbol":"lp-sscrt-srsr","label":"LP-SSCRT-SRSR"},"_id":"662b76941fcacc1215cbe8e6"},{"name":"LP-SSCRT-SYFI","address":"secret1he6rzcet6jcwryu544a5zkkadxee4sk0umu703","decimals":6,"hidden":true,"usage":["LPSTAKING"],"price":"0","id":"lp-sscrt-syfi","display_props":{"image":"/static/scrt.svg","symbol":"lp-sscrt-syfi","label":"LP-SSCRT-SYFI"},"_id":"662b76941fcacc10accbe8e7"},{"name":"LP-SSCRT-SUNI","address":"secret1m8msletvevuj2vsl8rcvqq9esflxmmnd2lf7yd","decimals":6,"hidden":true,"usage":["LPSTAKING"],"price":"0","id":"lp-sscrt-suni","display_props":{"image":"/static/scrt.svg","symbol":"lp-sscrt-suni","label":"LP-SSCRT-SUNI"},"_id":"662b76941fcacc6d79cbe8e8"},{"name":"LP-SSCRT-SOCEAN","address":"secret1kduh3vlszmg3snq36k6s8l4v8s26z47m3q9haa","decimals":6,"hidden":true,"usage":["LPSTAKING"],"price":"0","id":"lp-sscrt-socean","display_props":{"image":"/static/scrt.svg","symbol":"lp-sscrt-socean","label":"LP-SSCRT-SOCEAN"},"_id":"662b76941fcacc024fcbe8e9"},{"name":"LP-SSCRT-SUSDT","address":"secret1cgd6gcc4uyrxmzsmk4tpeta8auzcgwk4n5ngrx","decimals":6,"hidden":true,"usage":["LPSTAKING"],"price":"0","id":"lp-sscrt-susdt","display_props":{"image":"/static/scrt.svg","symbol":"lp-sscrt-susdt","label":"LP-SSCRT-SUSDT"},"_id":"662b76941fcacc0e85cbe8ea"},{"name":"LP-sSCRT-SBNB","address":"secret1le3d0fgkrzd433fdnetdqslfxmugvg0tuaqspe","decimals":6,"hidden":true,"usage":["LPSTAKING"],"price":"0","id":"lp-sscrt-sbnb","display_props":{"image":"/static/scrt.svg","symbol":"lp-sscrt-sbnb","label":"LP-SSCRT-SBNB"},"_id":"662b76941fcacc2003cbe8eb"},{"name":"LP-SSCRT-SDOT(BSC)","address":"secret1mc656zt6g37u2ufqp2tw8kaj5jxpujylfzw8yw","decimals":6,"hidden":true,"usage":["LPSTAKING"],"price":"0","id":"lp-sscrt-sdot(bsc)","display_props":{"image":"/static/scrt.svg","symbol":"lp-sscrt-sdot(bsc)","label":"LP-SSCRT-SDOT(BSC)"},"_id":"662b76941fcacc5563cbe8ec"},{"name":"LP-SSCRT-SMANA","address":"secret1gewshds6yhyry842vnxl9q6krezaatep6rxyt2","decimals":6,"hidden":true,"usage":["LPSTAKING"],"price":"0","id":"lp-sscrt-smana","display_props":{"image":"/static/scrt.svg","symbol":"lp-sscrt-smana","label":"LP-SSCRT-SMANA"},"_id":"662b76941fcacc8ff2cbe8ed"},{"name":"LP-SSCRT-SETH","address":"secret17gja535zp09t9mlzzxndqqg4gzvhg0vsklhd54","decimals":6,"hidden":true,"usage":["LPSTAKING"],"price":"0","id":"lp-sscrt-seth","display_props":{"image":"/static/scrt.svg","symbol":"lp-sscrt-seth","label":"LP-SSCRT-SETH"},"_id":"662b76941fcacc3649cbe8ee"},{"name":"LP-SSCRT-SLINK","address":"secret1rldr66767a4gz3adkq2vgndwgnxlfqqae4fgen","decimals":6,"hidden":true,"usage":["LPSTAKING"],"price":"0","id":"lp-sscrt-slink","display_props":{"image":"/static/scrt.svg","symbol":"lp-sscrt-slink","label":"LP-SSCRT-SLINK"},"_id":"662b76941fcacc728fcbe8ef"},{"name":"LP-SSCRT-SRUNE","address":"secret1kg24nc3v4wm4vzufup8fvmvffxtm8425uwfvqd","decimals":6,"hidden":true,"usage":["LPSTAKING"],"price":"0","id":"lp-sscrt-srune","display_props":{"image":"/static/scrt.svg","symbol":"lp-sscrt-srune","label":"LP-SSCRT-SRUNE"},"_id":"662b76941fcacc091ecbe8f0"},{"name":"LP-SETH-SETH(BSC)","address":"secret1c9ky0x6fj5gc0qw6tedxsng50mjl3szn7xhjeu","decimals":6,"hidden":true,"usage":["LPSTAKING"],"price":"0","id":"lp-seth-seth(bsc)","display_props":{"image":"/static/scrt.svg","symbol":"lp-seth-seth(bsc)","label":"LP-SETH-SETH(BSC)"},"_id":"662b76941fcacca5c1cbe8f1"},{"name":"LP-SSCRT-SWBTC","address":"secret1xxvqanj85m7dppplku5782cn9hl8askqd329sv","decimals":6,"hidden":true,"usage":["LPSTAKING"],"price":"0","id":"lp-sscrt-swbtc","display_props":{"image":"/static/scrt.svg","symbol":"lp-sscrt-swbtc","label":"LP-SSCRT-SWBTC"},"_id":"662b76941fcaccaed3cbe8f2"},{"name":"LP-SSCRT-SDAI","address":"secret17w0wjempgtt8ngn59y7cwlae02kve5jzar4xmw","decimals":6,"hidden":true,"usage":["LPSTAKING"],"price":"0","id":"lp-sscrt-sdai","display_props":{"image":"/static/scrt.svg","symbol":"lp-sscrt-sdai","label":"LP-SSCRT-SDAI"},"_id":"662b76941fcacc50d9cbe8f3"},{"name":"LP-SEFI-SXMR","address":"secret1xug4dc46sqlcaetm5c72qhjtedh05922uac9k2","decimals":6,"hidden":true,"usage":["LPSTAKING"],"price":"253.2700","id":"lp-sefi-sxmr","display_props":{"image":"/static/scrt.svg","symbol":"lp-sefi-sxmr","label":"LP-SEFI-SXMR"},"_id":"662b76941fcacc119bcbe8f4"},{"name":"sXMR","address":"secret19ungtd2c7srftqdwgq0dspwvrw63dhu79qxv88","decimals":12,"hidden":false,"usage":["SWAP"],"price":"147.1200","id":"sxmr","display_props":{"image":"/static/sXMR.png","symbol":"XMR","label":"sXMR"},"_id":"662b76941fcacc11c4cbe8f5"},{"name":"LP-SEFI-SUSDC","address":"secret1mm7df4ygxwlfg0l70jrrkshlhtp8vv5n7hj9rr","decimals":6,"hidden":true,"usage":["LPSTAKING"],"price":"0","id":"lp-sefi-susdc","display_props":{"image":"/static/scrt.svg","symbol":"lp-sefi-susdc","label":"LP-SEFI-SUSDC"},"_id":"662b76941fcacc0b87cbe8f6"},{"name":"LP-SUSDC-SUSDC(BSC)","address":"secret163e9frya0vqar70s4j3na94apf0cffl2rjgmgg","decimals":6,"hidden":true,"usage":["LPSTAKING"],"price":"0","id":"lp-susdc-susdc(bsc)","display_props":{"image":"/static/scrt.svg","symbol":"lp-susdc-susdc(bsc)","label":"LP-SUSDC-SUSDC(BSC)"},"_id":"662b76941fcacc98eecbe8f7"},{"name":"LP-SEFI-SATOM","address":"secret1w8l6c4fgc4nj2nwxadpmza4kt44xzd72pjn29u","decimals":6,"hidden":true,"usage":["LPSTAKING"],"price":"0","id":"lp-sefi-satom","display_props":{"image":"/static/scrt.svg","symbol":"lp-sefi-satom","label":"LP-SEFI-SATOM"},"_id":"662b76941fcaccaaefcbe8f8"},{"name":"LP-SEFI-SLUNA","address":"secret1ff99syuvgpfj5pdg8vw88c6lz796lclvyu3hem","decimals":6,"hidden":true,"usage":["LPSTAKING"],"price":"0","id":"lp-sefi-sluna","display_props":{"image":"/static/scrt.svg","symbol":"lp-sefi-sluna","label":"LP-SEFI-SLUNA"},"_id":"662b76941fcacc4c37cbe8f9"},{"name":"LP-SEFI-SOSMO","address":"secret13zae8r3zlms9e6f4gvy2252w2z5ffqxslu35wu","decimals":6,"hidden":true,"usage":["LPSTAKING"],"price":"0","id":"lp-sefi-sosmo","display_props":{"image":"/static/scrt.svg","symbol":"lp-sefi-sosmo","label":"LP-SEFI-SOSMO"},"_id":"662b76941fcacc1fe5cbe8fa"},{"name":"LP-SEFI-SDVPN","address":"secret1prxa3js02lys75a48hru944j5knszzr5tyehar","decimals":6,"hidden":true,"usage":["LPSTAKING"],"price":"0","id":"lp-sefi-sdvpn","display_props":{"image":"/static/scrt.svg","symbol":"lp-sefi-sdvpn","label":"LP-SEFI-SDVPN"},"_id":"662b76941fcacc195acbe8fb"},{"name":"LP-SSCRT-SALTER","address":"secret1zanftm9le27ge9lgmpx7mhjejsuss07ps3zg08","decimals":6,"hidden":true,"usage":["LPSTAKING"],"price":"0","id":"lp-sscrt-alter","display_props":{"image":"/static/scrt.svg","symbol":"lp-sscrt-alter","label":"LP-SSCRT-ALTER"},"_id":"662b76941fcacc3ef6cbe8fc"},{"name":"LP-SALTER-SUSDC","address":"secret10aajxql6mzn09t4t3kccuhp0tdl3yx6shtvk25","decimals":6,"hidden":true,"usage":["LPSTAKING"],"price":"0","id":"lp-alter-susdc","display_props":{"image":"/static/scrt.svg","symbol":"lp-alter-susdc","label":"LP-ALTER-SUSDC"},"_id":"662b76941fcacc02c5cbe8fd"},{"name":"ALTER","address":"secret12rcvz0umvk875kd6a803txhtlu7y0pnd73kcej","decimals":6,"hidden":false,"usage":["SWAP"],"price":"0.0283","id":"alter","display_props":{"image":"/static/scrt.svg","symbol":"ALTER","label":"ALTER"},"dst_address":"secret12rcvz0umvk875kd6a803txhtlu7y0pnd73kcej","_id":"662b76941fcacc22d2cbe8fe"},{"name":"SHD","address":"secret1qfql357amn448duf5gvp9gr48sxx9tsnhupu3d","decimals":8,"hidden":false,"usage":["SWAP"],"price":"10.4556","id":"shd","display_props":{"image":"/static/scrt.svg","symbol":"SHD","label":"SHD"},"dst_address":"secret1qfql357amn448duf5gvp9gr48sxx9tsnhupu3d","_id":"662b76941fcacc6c56cbe8ff"},{"name":"LP-SSCRT-SSHD","address":"secret1w2mepypw2fchq2zy8azl9ktmyrdyly3pa02d0h","decimals":6,"hidden":true,"usage":["LPSTAKING"],"price":"0","id":"lp-sscrt-shd","display_props":{"image":"/static/scrt.svg","symbol":"lp-sscrt-shd","label":"LP-sSCRT-SHD"},"_id":"662b76941fcacc8973cbe900"}]}